<Updates>
 <ApplicationName>{AnyApplication}</ApplicationName>
 <ApplicationVersion>1.0.0</ApplicationVersion>
 <Checksum>true</Checksum>
 <PackageUpdate>
  <Name>ControlerHost_V1.0.0</Name>
  <DisplayName>ControlerHost</DisplayName>
  <Description>Core Program@Version:1.0.0</Description>
  <Version>1.0.0</Version>
  <ReleaseDate>2025-05-26</ReleaseDate>
  <Script>installscript.js</Script>
  <Default>false</Default>
  <UpdateFile CompressedSize="24578717" OS="Any" UncompressedSize="86441369"/>
  <DownloadableArchives>config.7z,generic.7z,iconengines.7z,imageformats.7z,networkinformation.7z,platforms.7z,styles.7z,tls.7z,translations.7z,content.7z</DownloadableArchives>
  <SHA1>555607eb262ddc1a6d580c36b7d78840ba4d50cd</SHA1>
 </PackageUpdate>
 <PackageUpdate>
  <Name>ControlerHost_V1.0.1</Name>
  <DisplayName>ControlerHost</DisplayName>
  <Description>Core Program@Version:1.0.1</Description>
  <Version>1.0.1</Version>
  <ReleaseDate>2025-05-26</ReleaseDate>
  <Script>installscript.js</Script>
  <Default>false</Default>
  <UpdateFile CompressedSize="24578697" OS="Any" UncompressedSize="86441369"/>
  <DownloadableArchives>config.7z,generic.7z,iconengines.7z,imageformats.7z,networkinformation.7z,platforms.7z,styles.7z,tls.7z,translations.7z,content.7z</DownloadableArchives>
  <SHA1>a638499419ba95680efdf6fb234f40e187cbc9a7</SHA1>
 </PackageUpdate>
 <SHA1>249684a43c0e7a52d8ea5b90a4187b674af1ff2d</SHA1>
 <MetadataName>2025-05-26-2051_meta.7z</MetadataName>
</Updates>
